imem/i_mem.v
module i_mem(
    input  wire [31:0]  pc,
    output wire [31:0]  inst
);


parameter DATA_WIDTH = 32;
parameter ARRAY_SIZE = 100;
parameter FILENAME = "/home/hugo/code/verilog/riscv/imem/inst/inst.hex";  // program machine code

reg [DATA_WIDTH-1:0] imem [0:ARRAY_SIZE-1];

integer file, r, i;
reg [DATA_WIDTH*2:0] line;  // Registers large enough to store one line of data (hexadecimal string)
reg [DATA_WIDTH-1:0] value;

initial begin
    for (i = 0; i < ARRAY_SIZE; i = i + 1) begin
        imem[i] = 0;
    end
    
    // open file
    file = $fopen(FILENAME, "r");
    if (file == 0) begin
        $display("Error: Could not open file %s", FILENAME);
        $finish;
    end
    
    // read in file line by line
    i = 0;
    while (!$feof(file) && i < ARRAY_SIZE) begin
        r = $fgets(line, file);
        if (r != 0) begin
            r = $sscanf(line, "%h", value);
            if (r == 1) begin
                imem[i] = value;
                i = i + 1;
            end
        end
    end
    
    // close file
    $fclose(file);
    $display("Finish Reading!");
    
    // print
    // for (i = 0; i < ARRAY_SIZE; i = i + 1) begin
    //     $display("imem[%0d] = %h", i, imem[i]);
    // end
    // $finish;
end

assign inst = imem[pc/4];

endmodule

kernel/IF.v
module IF(
    input  wire         clk,
    input  wire         rst,
    input  wire [31:0]  EXMEM_d_ALUout,
    
    input  wire         EXMEM_c_SelPC,
    
    output wire [31:0]  IFID_d_inst,
    output wire [31:0]  IFID_d_pc
);


reg [31:0] pc;  // now pc

// PC candidate: EXMEM_c_SelPC
parameter NEXTPC = 1'b0;
parameter JUMPPC = 1'b1;

// i-memrey, addressing by Byte.
i_mem u_i_mem(
    .pc(pc),
    .inst(IFID_d_inst)  // output IFID_d_inst (END)
);

always @(posedge clk or negedge rst) begin
    if (~rst) begin  // rst = 0, reset 
        pc <= 0;
    end else begin 
        case(EXMEM_c_SelPC)  // update pc
            NEXTPC: 
                pc <= pc + 4;
            JUMPPC:
                pc <= EXMEM_d_ALUout;
            default:
                pc <= pc + 4;
        endcase
    end
end

assign IFID_d_pc = pc;  // output IFID_d_pc (END)

endmodule

kernel/test_stages/t_IF/testbench_IF.v
`timescale 1ns/1ns

module t_IF();

reg         clk = 0;
reg         rst = 0;
reg [31:0]  EXMEM_d_ALUout = 25;

reg         EXMEM_c_SelPC = 0; // 0: not jump, 1: jump

wire [31:0] IFID_d_inst_update;
wire [31:0] IFID_d_pc_update;

reg  [31:0] IFID_d_inst;
reg  [31:0] IFID_d_pc;

always #5 clk = ~clk;

IF uIF(
    .clk(clk),
    .rst(rst),
    .EXMEM_d_ALUout(EXMEM_d_ALUout),
    
    .EXMEM_c_SelPC(EXMEM_c_SelPC),
    
    .IFID_d_inst(IFID_d_inst_update),
    .IFID_d_pc(IFID_d_pc_update)
);

initial begin
    $dumpfile("t_IF");
    $dumpvars();
    #20;
    rst <= 1; // begin
    
    #40;
    EXMEM_c_SelPC <= 1;
    
    
    #125;
    $finish;
end 


always @(*) begin  // excute ended
    IFID_d_inst    <= IFID_d_inst_update;
    IFID_d_pc      <= IFID_d_pc_update;
    EXMEM_c_SelPC  <= 0;
    EXMEM_d_ALUout <= 3*4;
end


assign Updata = (IFID_d_inst == IFID_d_inst_update) & (IFID_d_pc_update == IFID_d_pc);

always @(posedge clk) begin  // print info
    $display("time: %t, clk: %b, rst: %b, IFID_d_inst: %h, IFID_d_pc: %d, EXMEM_c_SelPC: %d, EXMEM_d_ALUout: %d, Update: %b", $time, clk, rst, IFID_d_inst, IFID_d_pc, EXMEM_c_SelPC, EXMEM_d_ALUout, Updata);
end


endmodule

kernel/test_stages/t_IF/t_IF.vcd
$date
	Fri Jun 28 12:08:56 2024
$end
$version
	Icarus Verilog
$end
$timescale
	1ns
$end
$scope module t_IF $end
$var wire 1 ! Updata $end
$var wire 32 " IFID_d_pc_update [31:0] $end
$var wire 32 # IFID_d_inst_update [31:0] $end
$var reg 1 $ EXMEM_c_SelPC $end
$var reg 32 % EXMEM_d_ALUout [31:0] $end
$var reg 32 & IFID_d_inst [31:0] $end
$var reg 32 ' IFID_d_pc [31:0] $end
$var reg 1 ( clk $end
$var reg 1 ) rst $end
$scope module uIF $end
$var wire 1 $ EXMEM_c_SelPC $end
$var wire 32 * EXMEM_d_ALUout [31:0] $end
$var wire 32 + IFID_d_pc [31:0] $end
$var wire 1 ( clk $end
$var wire 1 ) rst $end
$var wire 32 , IFID_d_inst [31:0] $end
$var reg 32 - pc [31:0] $end
$scope module u_i_mem $end
$var wire 32 . inst [31:0] $end
$var wire 32 / pc [31:0] $end
$var reg 65 0 line [64:0] $end
$var reg 32 1 value [31:0] $end
$var integer 32 2 file [31:0] $end
$var integer 32 3 i [31:0] $end
$var integer 32 4 r [31:0] $end
$upscope $end
$upscope $end
$upscope $end
$enddefinitions $end
#0
$dumpvars
b0 4
b1001 3
b10000000000000000000000000000011 2
b1000000001100111 1
b1010 0
b0 /
b101000000000001010110011 .
b0 -
b101000000000001010110011 ,
b0 +
b1100 *
0)
0(
b0 '
b101000000000001010110011 &
b1100 %
0$
b101000000000001010110011 #
b0 "
1!
$end
#5
1(
#10
0(
#15
1(
#20
1)
0(
#25
b100 '
b1100010011 &
1!
b1100010011 #
b1100010011 ,
b1100010011 .
b100 "
b100 +
b100 -
b100 /
1(
#30
0(
#35
b1000 '
b101100000000001110110011 &
1!
b101100000000001110110011 #
b101100000000001110110011 ,
b101100000000001110110011 .
b1000 "
b1000 +
b1000 -
b1000 /
1(
#40
0(
#45
b1100 '
b11100110101101001100011 &
1!
b11100110101101001100011 #
b11100110101101001100011 ,
b11100110101101001100011 .
b1100 "
b1100 +
b1100 -
b1100 /
1(
#50
0(
#55
b10000 '
b11000101010000000100011 &
1!
b11000101010000000100011 #
b11000101010000000100011 ,
b11000101010000000100011 .
b10000 "
b10000 +
b10000 -
b10000 /
1(
#60
1$
0(
#65
0$
b1100 '
b11100110101101001100011 &
1!
b11100110101101001100011 #
b11100110101101001100011 ,
b11100110101101001100011 .
b1100 "
b1100 +
b1100 -
b1100 /
1(
#70
0(
#75
b10000 '
b11000101010000000100011 &
1!
b11000101010000000100011 #
b11000101010000000100011 ,
b11000101010000000100011 .
b10000 "
b10000 +
b10000 -
b10000 /
1(
#80
0(
#85
b10100 '
b100110000001100010011 &
1!
b100110000001100010011 #
b100110000001100010011 ,
b100110000001100010011 .
b10100 "
b10100 +
b10100 -
b10100 /
1(
#90
0(
#95
b11000 '
b10000101000001010010011 &
1!
b10000101000001010010011 #
b10000101000001010010011 ,
b10000101000001010010011 .
b11000 "
b11000 +
b11000 -
b11000 /
1(
#100
0(
#105
b11100 '
b11111111000111111111000001101111 &
1!
b11111111000111111111000001101111 #
b11111111000111111111000001101111 ,
b11111111000111111111000001101111 .
b11100 "
b11100 +
b11100 -
b11100 /
1(
#110
0(
#115
b100000 '
b1000000001100111 &
1!
b1000000001100111 #
b1000000001100111 ,
b1000000001100111 .
b100000 "
b100000 +
b100000 -
b100000 /
1(
#120
0(
#125
b100100 '
b0 &
1!
b0 #
b0 ,
b0 .
b100100 "
b100100 +
b100100 -
b100100 /
1(
#130
0(
#135
b101000 '
1!
b101000 "
b101000 +
b101000 -
b101000 /
1(
#140
0(
#145
b101100 '
1!
b101100 "
b101100 +
b101100 -
b101100 /
1(
#150
0(
#155
b110000 '
1!
b110000 "
b110000 +
b110000 -
b110000 /
1(
#160
0(
#165
b110100 '
1!
b110100 "
b110100 +
b110100 -
b110100 /
1(
#170
0(
#175
b111000 '
1!
b111000 "
b111000 +
b111000 -
b111000 /
1(
#180
0(
#185
b111100 '
1!
b111100 "
b111100 +
b111100 -
b111100 /
1(
